regcensus/__init__.py
regcensus/api.py
regcensus/cache.py
regcensus-1.1.0.dist-info/LICENSE
regcensus-1.1.0.dist-info/METADATA
regcensus-1.1.0.dist-info/WHEEL
regcensus-1.1.0.dist-info/top_level.txt
regcensus-1.1.0.dist-info/RECORD
