Metadata-Version: 2.1
Name: regcensus
Version: 1.1.0
Summary: Python package for accessing data from the QuantGov API
Home-page: https://github.com/QuantGov/regcensus-api-python
Author: QuantGov
Author-email: quantgov.info@gmail.com
Classifier: Programming Language :: Python :: 3
Classifier: License :: OSI Approved :: MIT License
Classifier: Operating System :: OS Independent
License-File: LICENSE
Requires-Dist: pandas
Requires-Dist: requests
